nugraph/__init__.py
nugraph/meta.yaml
nugraph/data/BalanceSampler.py
nugraph/data/__init__.py
nugraph/data/data_module.py
nugraph/data/dataset.py
nugraph/models/__init__.py
nugraph/models/nugraph2/__init__.py
nugraph/models/nugraph2/decoders.py
nugraph/models/nugraph2/encoder.py
nugraph/models/nugraph2/linear.py
nugraph/models/nugraph2/nexus.py
nugraph/models/nugraph2/nugraph2.py
nugraph/models/nugraph2/plane.py
nugraph/models/nugraph2/transform.py
nugraph/models/nugraph3/__init__.py
nugraph/models/nugraph3/core.py
nugraph/models/nugraph3/encoder.py
nugraph/models/nugraph3/nugraph3.py
nugraph/models/nugraph3/transform.py
nugraph/models/nugraph3/types.py
nugraph/models/nugraph3/decoders/__init__.py
nugraph/models/nugraph3/decoders/event.py
nugraph/models/nugraph3/decoders/filter.py
nugraph/models/nugraph3/decoders/instance.py
nugraph/models/nugraph3/decoders/semantic.py
nugraph/models/nugraph3/decoders/spacepoint.py
nugraph/models/nugraph3/decoders/vertex.py
nugraph/util/LogCoshLoss.py
nugraph/util/ObjCondensationLoss.py
nugraph/util/RecallLoss.py
nugraph/util/__init__.py
nugraph/util/event_labels.py
nugraph/util/hierarchical_edges.py
nugraph/util/input_norm.py
nugraph/util/position_features.py
nugraph/util/scriptutils.py
nugraph-25.4.0.dist-info/licenses/LICENSE
nugraph-25.4.0.dist-info/WHEEL
nugraph-25.4.0.dist-info/METADATA
nugraph-25.4.0.dist-info/RECORD
