Metadata-Version: 2.4
Name: nugraph
Version: 25.4.0
Summary: NuGraph2: A Graph Neural Network for neutrino physics event reconstruction
Author-email: v hewes <vhewes@fnal.gov>
Requires-Python: >=3.10
Classifier: Intended Audience :: Science/Research
Classifier: License :: OSI Approved :: MIT License
License-File: LICENSE
Requires-Dist: cuml-cu12
Requires-Dist: matplotlib
Requires-Dist: plotly
Requires-Dist: pynuml==24.7.dev1
Requires-Dist: pynvml
Requires-Dist: seaborn
Requires-Dist: torch>=1.12.1
Requires-Dist: torch-geometric>=2.1.0
Requires-Dist: torch-scatter
Requires-Dist: pytorch-lightning>=1.7.1
Requires-Dist: wandb
Project-URL: Home, https://github.com/vhewes/nugraph
